{"frames":{"beak0":{"frame":{"x":355,"y":568,"w":85,"h":60},"rotated":false,"trimmed":false,"spriteSourceSize":{"x":0,"y":0,"w":85,"h":60},"sourceSize":{"w":85,"h":60}},"beak1":{"frame":{"x":710,"y":636,"w":87,"h":83},"rotated":false,"trimmed":false,"spriteSourceSize":{"x":0,"y":0,"w":87,"h":83},"sourceSize":{"w":87,"h":83}},"body":{"frame":{"x":355,"y":0,"w":530,"h":427},"rotated":false,"trimmed":false,"spriteSourceSize":{"x":0,"y":0,"w":530,"h":427},"sourceSize":{"w":530,"h":427}},"eyes":{"frame":{"x":572,"y":432,"w":111,"h":74},"rotated":false,"trimmed":false,"spriteSourceSize":{"x":0,"y":0,"w":111,"h":74},"sourceSize":{"w":111,"h":74}},"leg":{"frame":{"x":710,"y":724,"w":141,"h":112},"rotated":false,"trimmed":false,"spriteSourceSize":{"x":0,"y":0,"w":141,"h":112},"sourceSize":{"w":141,"h":112}},"pupils":{"frame":{"x":445,"y":568,"w":94,"h":47},"rotated":false,"trimmed":false,"spriteSourceSize":{"x":0,"y":0,"w":94,"h":47},"sourceSize":{"w":94,"h":47}},"wing":{"frame":{"x":355,"y":432,"w":212,"h":131},"rotated":false,"trimmed":false,"spriteSourceSize":{"x":0,"y":0,"w":212,"h":131},"sourceSize":{"w":212,"h":131}},"wing1":{"frame":{"x":355,"y":636,"w":350,"h":207},"rotated":false,"trimmed":false,"spriteSourceSize":{"x":0,"y":0,"w":350,"h":207},"sourceSize":{"w":350,"h":207}},"wing2":{"frame":{"x":0,"y":424,"w":350,"h":207},"rotated":false,"trimmed":false,"spriteSourceSize":{"x":0,"y":0,"w":350,"h":207},"sourceSize":{"w":350,"h":207}},"wing3":{"frame":{"x":0,"y":212,"w":350,"h":207},"rotated":false,"trimmed":false,"spriteSourceSize":{"x":0,"y":0,"w":350,"h":207},"sourceSize":{"w":350,"h":207}},"wing4":{"frame":{"x":0,"y":636,"w":350,"h":207},"rotated":false,"trimmed":false,"spriteSourceSize":{"x":0,"y":0,"w":350,"h":207},"sourceSize":{"w":350,"h":207}},"wing5":{"frame":{"x":0,"y":0,"w":350,"h":207},"rotated":false,"trimmed":false,"spriteSourceSize":{"x":0,"y":0,"w":350,"h":207},"sourceSize":{"w":350,"h":207}}},"meta":{"app":"http://www.leshylabs.com/apps/sstool/","version":"Leshy SpriteSheet Tool v0.8.4","image":"spritesheet.png","size":{"w":885,"h":843},"scale":1}}